pyphantomapi/__init__.py
pyphantomapi/phantom.py
pyphantomapi-1.0.0.dist-info/LICENSE.md
pyphantomapi-1.0.0.dist-info/METADATA
pyphantomapi-1.0.0.dist-info/WHEEL
pyphantomapi-1.0.0.dist-info/top_level.txt
pyphantomapi-1.0.0.dist-info/RECORD
