Metadata-Version: 2.1
Name: pyphantomapi
Version: 1.0.0
Summary: Python Wrapper for the Splunk Phantom API
Home-page: https://github.com/ryanplasma/pyphantomapi
Author: Ryan Plas
Author-email: ryan@wordplas.com
License: MIT
Platform: UNKNOWN
Requires-Dist: requests
